{
	"dependencies": "thermalfoundation",
	"populate": {
		"rockcrystals": {
			"distribution": "uniform",
			"generator": {
				"block": {
					"name": "astralsorcery:blockcustomore",
					"metadata": 0
				},
				"material": "minecraft:stone",
				"cluster-size": 2
			},
			"cluster-count": 8,
			"min-height": 0,
			"max-height": 42,
			"retrogen": true,
			"biome": "all",
			"dimension": {
				"restriction": "whitelist",
				"value": [
					89
				]
			}
		},
		"aqumarine_sand": {
			"enabled": "true",
			"distribution": "uniform",
			"generator": {
				"block": [
					{
						"name": "astralsorcery:blockcustomsandore",
						"weight": 40
					},
					{
						"name": "minecraft:sand",
						"weight": 60
					}
				],
				"material": "minecraft:stone",
				"cluster-size": 14
			},
			"cluster-count": 20,
			"min-height": 0,
			"max-height": 64,
			"retrogen": "true",
			"biome": "all",
			"dimension": {
				"restriction": "whitelist",
				"value": [
					89
				]
			}
		},
		"lunarplane_iron_ore": {
			"distribution": "uniform",
			"generator": {
				"block": "iron_ore",
				"material": "minecraft:stone",
				"cluster-size": 12
			},
			"cluster-count": 26,
			"min-height": 0,
			"max-height": 64,
			"retrogen": false,
			"biome": "all",
			"dimension": {
				"restriction": "whitelist",
				"value": [
					89
				]
			}
		},
	}
}